README.md
setup.py
TOPSIS_Purnima_101803523.egg-info/PKG-INFO
TOPSIS_Purnima_101803523.egg-info/SOURCES.txt
TOPSIS_Purnima_101803523.egg-info/dependency_links.txt
TOPSIS_Purnima_101803523.egg-info/entry_points.txt
TOPSIS_Purnima_101803523.egg-info/requires.txt
TOPSIS_Purnima_101803523.egg-info/top_level.txt
src/topsis.py