Metadata-Version: 2.1
Name: TOPSIS-Purnima-101803523
Version: 1.0.2
Summary: A Python package to implement TOPSIS.
Home-page: https://pypi.org/project/TOPSIS-Purnima-101803523
Author: Purnima Lal
Author-email: purnimalal009@gmail.com
License: MIT
Platform: UNKNOWN
Classifier: License :: OSI Approved :: MIT License
Classifier: Programming Language :: Python :: 3
Classifier: Programming Language :: Python :: 3.4
Classifier: Programming Language :: Python :: 3.5
Classifier: Programming Language :: Python :: 3.6
Classifier: Programming Language :: Python :: 3.7
